anura/__init__.py
anura/direct/__init__.py
anura/direct/client.py
anura/direct/exceptions.py
anura/direct/result.py
anura-2.0.0.dist-info/METADATA
anura-2.0.0.dist-info/WHEEL
anura-2.0.0.dist-info/licenses/LICENSE
anura-2.0.0.dist-info/RECORD
