Metadata-Version: 2.4
Name: anura
Version: 2.0.0
Summary: Anura SDK for Python
Project-URL: Homepage, https://github.com/anuraio/anura-sdk-python
Project-URL: Issues, https://github.com/anuraio/anura-sdk-python/issues
Author-email: Xavier Mejia <geekpad@anura.io>
License-File: LICENSE
Requires-Python: >=3.10
Requires-Dist: aiohttp
Requires-Dist: requests
